<INDIVIDUAL>
<ID>train_subject7042</ID>
<WRITING>
	<TITLE>   </TITLE>
	<DATE> 2015-01-16 02:16:32 </DATE>
	<INFO> reddit post </INFO>
	<TEXT> -"This is getting us nowhere.
Can we move on to the DNA test, please? That's a good idea.
DNA's good."
-"Yeah, I can't do that."
-"What do you mean? - Aren't you a scientist?"
-"No, I'm an Econ major.
I just wanted to look at some poop." </TEXT>
</WRITING>
<WRITING>
	<TITLE>   </TITLE>
	<DATE> 2014-12-29 08:19:06 </DATE>
	<INFO> reddit post </INFO>
	<TEXT> It's just perfect. </TEXT>
</WRITING>
<WRITING>
	<TITLE>   </TITLE>
	<DATE> 2014-12-29 08:14:38 </DATE>
	<INFO> reddit post </INFO>
	<TEXT> Fuck yeah ... Whatever makes you happy </TEXT>
</WRITING>
<WRITING>
	<TITLE>   </TITLE>
	<DATE> 2014-11-19 01:47:00 </DATE>
	<INFO> reddit post </INFO>
	<TEXT> Life Advice from porky's butthole. Def legit. </TEXT>
</WRITING>
</INDIVIDUAL>
